MANIFEST.in
setup.py
dbsxrchpro/__init__.py
dbsxrchpro.egg-info/PKG-INFO
dbsxrchpro.egg-info/SOURCES.txt
dbsxrchpro.egg-info/dependency_links.txt
dbsxrchpro.egg-info/requires.txt
dbsxrchpro.egg-info/top_level.txt