Metadata-Version: 2.1
Name: dbsxrchpro
Version: 0.1
Requires-Dist: requests>=2.25.1
